<?xml version="1.0" encoding="UTF-8"?>
<dictionary>
    <locale name="pl">
        <message key="ny16EventFilterLabel">noworoczne</message>
        <message key="ny16StageInfo">zadanie</message>
        <message key="ny16Exchange">wymiana meteorytów</message>
        <message key="npcNY16ActorBoyName">Badacz bieguna</message>
        <message key="npcNY16ActorGirlName">Badacz bieguna</message>
        <message key="ny16NpcStage1Message1">Napraw drzwi, bo wiatr wieje!</message>
        <message key="ny16NpcStage1Message2">Ależ wieje! To dziura, a nie wentylacja!</message>
        <message key="ny16NpcStage1Message3">Trzeba było lądować na południu...</message>
        <message key="ny16NpcStage2Message1">Ale błoto. Trzeba by się doprowadzić do ładu, co?</message>
        <message key="ny16NpcStage2Message2">Masz znajomych? Może ich zaprosić?</message>
        <message key="ny16NpcStage2Message3">Nie można przejść, nie włażąc w kałużę.</message>
        <message key="ny16NpcStage3Message1">No i ten chłód! Kiedy rusza sezon grzewczy?</message>
        <message key="ny16NpcStage3Message2">Generator chyba działa. Może zatankować?</message>
        <message key="ny16NpcStage3Message3">Napalimy w piecu? Może zrobi się cieplej.</message>
        <message key="ny16NpcStage4Message1">Do otwarcia okna będziemy potrzebować pomocy.</message>
        <message key="ny16NpcStage4Message2">Nie, we dwójkę nie damy rady. Wołaj na pomoc!</message>
        <message key="ny16NpcStage4Message3">Zawołaj ludzi, to pomogą nam otworzyć okno.</message>
        <message key="ny16ToolBox">Zestaw narzędzi</message>
        <message key="ny16Meteorites">Meteoryty</message>
        <message key="ny16MeteoriteLootDescription">można zdobyć w ramach noworocznej promocji</message>
        <message key="newYear2016ExchangeMeteoriteDialogTitle">Wymiana na prezenty!</message>
        <message key="newYear2016ExchangeMeteoriteDialogMessage">Wymieniaj pozostałe meteoryty na noworoczne prezenty!</message>
        <message key="ny16ProgressDialogTitle">Noworoczne przygotowania</message>
        <message key="giftExchange">Wymiana meteorytów na prezenty</message>
        <message key="ny16gnr">Generator energii</message>
        <message key="ny16stage">:stage: etap</message>
        <message key="goToCraftDialog">do pracowni</message>
        <message key="makeToolBox">zrób</message>
        <message key="askHelp">poproś o pomoc</message>
        <message key="stageComplete">zakończ</message>
        <message key="ny16meteoriteExchangeTitle">Noworoczne prezenty!</message>
        <message key="ny16meteoriteExchangeMessage">Meteoryty, które ci zostały, zmieniły się w prezenty.</message>
        <message key="ny16UseWindowWarning">Nie można otworzyć okna</message>
        <message key="ny16UseWindowNotEnoughPeoplesToOpenWarning">Za mało ludzi do otwarcia okna. Zawołaj na pomoc znajomych!</message>
        <message key="ny16UseWindowNotEnoughMeteoritesWarning">Za mało meteorytów do otwarcia okna.</message>
        <message key="ny16st1sb1Description">Zbieraj odłamki meteorytów, aby stworzyć skrzynię z narzędziami</message>
        <message key="ny16st1sb2Description">Aby naprawić drzwi i wentylację, zbierz brakujące elementy do skrzyni z narzędziami</message>
        <message key="ny16st1sb3Description">Napraw drzwi, używając nowych narzędzi</message>
        <message key="ny16st1sb4Description">W oczekiwaniu na kolejny etap zbieraj dalej meteoryty i zmieniaj je w prezenty.</message>
        <message key="ny16st2sb1Description">Poproś znajomych o pomoc w sprzątaniu stacji</message>
        <message key="ny16st3sb1Description">Aby uruchomić generator, zbierz odłamki meteorytów</message>
        <message key="ny16st4sb1Description">Aby otworzyć okno, zbierz odłamki meteorytów</message>
        <message key="ny16st4sb2Description">Aby otworzyć okno, zawołaj znajomych i poproś ich, aby stanęli na znacznikach przy ścianie</message>
        <message key="ny16st4sb3Description">Do zakończenia noworocznej promocji możesz zbierać meteoryty i zmieniać je w prezenty.</message>
        <message key="newyear2016CreateRoomTitle">Utworzyć pokój?</message>
        <message key="newyear2016CreateRoomMessage">Rozwiąż zagadkę opuszczonej stacji polarnej i zdobądź przydatne przedmioty!</message>
        <message key="newyear2016CreateButton">zrób</message>
        <message key="newyear2016LaterButton">utwórz</message>
        <message key="newyear2016OpenButton">otwórz</message>
        <message key="newyear2016OpenWindowMessage">Twoi znajomi zajęli odpowiednie miejsca. Otworzyć okno?</message>
        <message key="newyear2016FriendGetMode">Utwórz wydarzenie lub zaproś znajomych do sprzątania stacji polarnej.</message>
        <message key="newYear2016WelcomeDialogTitle">Święta nadciągają!</message>
        <message key="newYear2016WelcomeDialogMessageTopRestoration">Współpracuj z innymi graczami na mapach, zbierz wystarczającą ilość meteorytów i zrób z nich narzędzia.</message>
        <message key="newYear2016WelcomeDialogMessageTopClean">Zaproś znajomych w gości.</message>
        <message key="newYear2016WelcomeDialogMessageTopFuel">Współpracuj z innymi graczami na mapach, zbierz wystarczającą ilość meteorytów do zatankowania generatora.</message>
        <message key="newYear2016WelcomeDialogMessageTopRepair">Współpracuj z innymi graczami na mapach, zbierz wystarczającą ilość meteorytów do naprawy okna.</message>
        <message key="newYear2016WelcomeDialogMessageMiddleRestoration">Wyeliminuj przeciąg, naprawiając drzwi i kratkę wentylacyjną.</message>
        <message key="newYear2016WelcomeDialogMessageMiddleClean">Posprzątajcie wszyscy razem, aby pomieszczenie było czyste.</message>
        <message key="newYear2016WelcomeDialogMessageMiddleFuel">Napraw generator, aby narzędzia zadziałały.</message>
        <message key="newYear2016WelcomeDialogMessageMiddleRepair">Znajdź wiernych towarzyszy i razem otwórzcie stare okienko.</message>
        <message key="newYear2016WelcomeDialogMessageBottomCommon">Zdobądź cenną nagrodę i zrób kolejny krok ku rozwiązaniu łamigłówki. W oczekiwaniu na kolejne zadania możesz wymieniać meteoryty na prezenty.</message>
        <message key="newYear2016WelcomeDialogMessageBottomResult">Zdobądź bardzo cenną nagrodę i zakończ promocję.</message>
        <message key="newYear2016AwardDialogMessage">Otrzymujesz ten wspaniały prezent w nagrodę za ukończenie etapu. Oby tak dalej! Podziel się tą nowością ze znajomymi!</message>
        <message key="newYear2016AskDialogTitle">Pomoc znajomych!</message>
        <message key="newYear2016AskDialogMessage">Poproś znajomych o posprzątanie twojej stacji polarnej</message>
        <message key="newYear2016WallMessage1">Udało mi się zdobyć wspaniały prezent w nagrodę za ukończenie etapu. Też taki chcesz? Czekam na ciebie w grze! :link:</message>
        <message key="newYear2016WallMessage2">Przyjaciele, chciałbym dostać wyjątkowy prezent w grze „Awataria” i potrzebuję waszej pomocy. Bez was mi się uda! :link:</message>
        <message key="newYear2016WallMessage3">Przyjaciele, bez was nie poradzę sobie z przygotowaniem stacji polarnej w grze „Awataria”. Czekam w grze! :link:</message>
        <message key="newYear2016LeftTime">do :stage: etapu
:time:</message>
    </locale>
</dictionary>